MANIFEST.in
README.md
setup.cfg
setup.py
nucosCR/__init__.py
nucosCR/cryptoaesbase.py
nucosCR/cryptorsabase.py
nucosCR/version.py
nucosCR.egg-info/PKG-INFO
nucosCR.egg-info/SOURCES.txt
nucosCR.egg-info/dependency_links.txt
nucosCR.egg-info/requires.txt
nucosCR.egg-info/top_level.txt
scripts/aes-cp
scripts/aes-cp.bat