Metadata-Version: 1.1
Name: nucosCR
Version: 0.2.7
Summary: nucosCR - convenient python crypto-tools
Home-page: https://github.com/DocBO/nucosCR
Author: Oliver Braun
Author-email: oliver.braun@nucos.de
License: MIT
Download-URL: https://github.com/DocBO/nucosCR/tarball/0.0.1
Keywords: cryptography
Platform: UNKNOWN
Classifier: Development Status :: 1 - Planning
Classifier: Environment :: Console
Classifier: License :: OSI Approved :: MIT License
Classifier: Natural Language :: English
Classifier: Operating System :: OS Independent
Classifier: Programming Language :: Python :: 2
Classifier: Programming Language :: Python :: 2.7
Classifier: Programming Language :: Python :: 3
Classifier: Programming Language :: Python :: 3.4
Classifier: Programming Language :: Python :: 3.5
